request_logging/__init__.py
request_logging/decorators.py
request_logging/middleware.py
django_request_logging-0.7.5.dist-info/LICENSE
django_request_logging-0.7.5.dist-info/METADATA
django_request_logging-0.7.5.dist-info/WHEEL
django_request_logging-0.7.5.dist-info/top_level.txt
django_request_logging-0.7.5.dist-info/RECORD
