Metadata-Version: 2.1
Name: django-request-logging
Version: 0.7.5
Summary: Django middleware that logs http request body.
Home-page: https://github.com/Rhumbix/django-request-logging.git
Author: Rhumbix
Author-email: dev@rhumbix.com
License: MIT
Platform: UNKNOWN
